{
  "id": 10125011,
  "name": "Constellar Tellarknights",
  "Stats": {
    "type": "Spell Card",
    "frameType": "spell",
    "race": "Continuous"
  },
  "Rulings": {
    "Edison": "No rulings found for this card. Request new rulings at https://discord.gg/shVJnYJNpg",
    "Tengu": "No rulings found for this card. Request new rulings at https://discord.gg/MmEZSNeTdX",
    "Goat": "No rulings available for this card.",
    "HAT": "No rulings available for this card.",
    "Vegas": "No rulings available for this card.",
    "Meadowlands": "No rulings available for this card.",
    "FireWater": "No rulings available for this card.",
    "Cat": "No rulings available for this card.",
    "TeleDAD": "No rulings available for this card.",
    "Gladiator": "No rulings available for this card.",
    "ReturnDAD": "No rulings available for this card.",
    "Trooper": "No rulings available for this card.",
    "Circle": "No rulings available for this card.",
    "Stein": "No rulings available for this card.",
    "Base": "No rulings available for this card."
  },
  "PSCT": {
    "Edison": "No rulings available for this card.",
    "Tengu": "No updated text available for this card.",
    "Goat": "No updated text available for this card.",
    "HAT": "No updated text available for this card.",
    "Vegas": "No updated text available for this card.",
    "Meadowlands": "No updated text available for this card.",
    "FireWater": "No updated text available for this card.",
    "Cat": "No updated text available for this card.",
    "TeleDAD": "No updated text available for this card.",
    "Gladiator": "No updated text available for this card.",
    "ReturnDAD": "No updated text available for this card.",
    "Trooper": "No updated text available for this card.",
    "Circle": "No updated text available for this card.",
    "Stein": "No updated text available for this card.",
    "Base": "When this card is activated: You can Special Summon 1 \"tellarknight\" or \"Constellar\" monster from your hand or GY. You can target 1 \"tellarknight\" or \"Constellar\" Xyz Monster you control; Special Summon from your Extra Deck, 1 \"tellarknight\" or \"Constellar\" Xyz Monster with a different Rank, by using that Xyz Monster you control as material. (This is treated as an Xyz Summon. Transfer its materials to the Summoned monster.) You can only use this effect of \"Constellar Tellarknights\" once per turn. You can only activate 1 \"Constellar Tellarknights\" per turn."
  }
}