{
  "id": 101206041,
  "name": "Number C32: Shark Drake Leviathan",
  "Stats": {
    "type": "XYZ Monster",
    "frameType": "xyz",
    "atk": 3100,
    "def": 2600,
    "level": 5,
    "race": "Sea Serpent",
    "attribute": "WATER"
  },
  "Rulings": {
    "Edison": "No rulings found for this card. Request new rulings at https://discord.gg/shVJnYJNpg",
    "Tengu": "No rulings found for this card. Request new rulings at https://discord.gg/MmEZSNeTdX",
    "Goat": "No rulings available for this card.",
    "HAT": "No rulings available for this card.",
    "Vegas": "No rulings available for this card.",
    "Meadowlands": "No rulings available for this card.",
    "FireWater": "No rulings available for this card.",
    "Cat": "No rulings available for this card.",
    "TeleDAD": "No rulings available for this card.",
    "Gladiator": "No rulings available for this card.",
    "ReturnDAD": "No rulings available for this card.",
    "Trooper": "No rulings available for this card.",
    "Circle": "No rulings available for this card.",
    "Stein": "No rulings available for this card.",
    "Base": "No rulings available for this card."
  },
  "PSCT": {
    "Edison": "No rulings available for this card.",
    "Tengu": "No updated text available for this card.",
    "Goat": "No updated text available for this card.",
    "HAT": "No updated text available for this card.",
    "Vegas": "No updated text available for this card.",
    "Meadowlands": "No updated text available for this card.",
    "FireWater": "No updated text available for this card.",
    "Cat": "No updated text available for this card.",
    "TeleDAD": "No updated text available for this card.",
    "Gladiator": "No updated text available for this card.",
    "ReturnDAD": "No updated text available for this card.",
    "Trooper": "No updated text available for this card.",
    "Circle": "No updated text available for this card.",
    "Stein": "No updated text available for this card.",
    "Base": "4 Level 5 monsters\r\nYou can also Xyz Summon this card by discarding 1 Spell and using 1 Rank 4 \"Shark Drake\" Xyz Monster you control. (Transfer its materials to this card.) Once per turn (Quick Effect): You can detach 1 material from this card, then target 1 Effect Monster your opponent controls; negate its effects, and if you do, change its ATK/DEF to 0. This card can make a second attack during each Battle Phase, also if it attacks a Defense Position monster, inflict piercing battle damage."
  }
}