{
  "id": 564541,
  "name": "Totem Dragon",
  "Stats": {
    "type": "Effect Monster",
    "frameType": "effect",
    "atk": 400,
    "def": 200,
    "level": 2,
    "race": "Dragon",
    "attribute": "EARTH"
  },
  "Rulings": {
    "Edison": "● You can use this card as 2 Tributes for a Tribute Set of a Dragon.\n● The ② effect is not \"once per turn\". It it is negated by \"Royal Oppression\", it can be activated again in a new chain.\n● If this card becomes flipped face-down or equipped to a monster, \"banish it if it leaves the field\" is no longer applied to it.",
    "Tengu": "● You can use this card as 2 Tributes for a Tribute Set of a Dragon.\n● The ② effect is not \"once per turn\". It it is negated by \"Royal Oppression\", it can be activated again in a new chain.\n● If this card becomes flipped face-down or equipped to a monster, \"banish it if it leaves the field\" is no longer applied to it.",
    "Goat": "No rulings found for this card. Request new rulings at https://discord.gg/shVJnYJNpg",
    "HAT": "No rulings found for this card. Request new rulings at https://discord.gg/shVJnYJNpg",
    "Vegas": "No rulings found for this card. Request new rulings at https://discord.gg/shVJnYJNpg",
    "Meadowlands": "No rulings found for this card. Request new rulings at https://discord.gg/shVJnYJNpg",
    "FireWater": "No rulings found for this card. Request new rulings at https://discord.gg/shVJnYJNpg",
    "Cat": "No rulings found for this card. Request new rulings at https://discord.gg/shVJnYJNpg",
    "TeleDAD": "No rulings found for this card. Request new rulings at https://discord.gg/shVJnYJNpg",
    "Gladiator": "No rulings found for this card. Request new rulings at https://discord.gg/shVJnYJNpg",
    "ReturnDAD": "No rulings found for this card. Request new rulings at https://discord.gg/shVJnYJNpg",
    "Trooper": "No rulings found for this card. Request new rulings at https://discord.gg/shVJnYJNpg",
    "Circle": "No rulings found for this card. Request new rulings at https://discord.gg/shVJnYJNpg",
    "Stein": "No rulings found for this card. Request new rulings at https://discord.gg/shVJnYJNpg",
    "Base": "No rulings found for this card. Request new rulings at https://discord.gg/shVJnYJNpg"
  },
  "PSCT": {
    "Edison": "① This card can be treated as 2 Tributes for the Tribute Summon/Set of a Dragon.\n② During your Standby Phase, if this is in your GY, you control no monsters, and all monsters in your GY are Dragons:\nYou can Special Summon this card (banish it if it leaves the field).",
    "Tengu": "① This card can be treated as 2 Tributes for the Tribute Summon/Set of a Dragon.\n② During your Standby Phase, if this is in your GY, you control no monsters, and all monsters in your GY are Dragons:\nYou can Special Summon this card (banish it if it leaves the field).",
    "Goat": "No updated text available for this card.",
    "HAT": "No updated text available for this card.",
    "Vegas": "No updated text available for this card.",
    "Meadowlands": "No updated text available for this card.",
    "FireWater": "No updated text available for this card.",
    "Cat": "No updated text available for this card.",
    "TeleDAD": "No updated text available for this card.",
    "Gladiator": "No updated text available for this card.",
    "ReturnDAD": "No updated text available for this card.",
    "Trooper": "No updated text available for this card.",
    "Circle": "No updated text available for this card.",
    "Stein": "No updated text available for this card."
  }
}