{
  "id": 64211118,
  "name": "Firewall Dragon Darkfluid - Neo Tempest Terahertz",
  "Stats": {
    "type": "Link Monster",
    "frameType": "link",
    "atk": 3000,
    "race": "Cyberse",
    "attribute": "DARK"
  },
  "Rulings": {
    "Edison": "No rulings found for this card. Request new rulings at https://discord.gg/shVJnYJNpg",
    "Tengu": "No rulings found for this card. Request new rulings at https://discord.gg/MmEZSNeTdX",
    "Goat": "No rulings available for this card.",
    "HAT": "No rulings available for this card.",
    "Vegas": "No rulings available for this card.",
    "Meadowlands": "No rulings available for this card.",
    "FireWater": "No rulings available for this card.",
    "Cat": "No rulings available for this card.",
    "TeleDAD": "No rulings available for this card.",
    "Gladiator": "No rulings available for this card.",
    "ReturnDAD": "No rulings available for this card.",
    "Trooper": "No rulings available for this card.",
    "Circle": "No rulings available for this card.",
    "Stein": "No rulings available for this card.",
    "Base": "No rulings available for this card."
  },
  "PSCT": {
    "Edison": "No rulings available for this card.",
    "Tengu": "No updated text available for this card.",
    "Goat": "No updated text available for this card.",
    "HAT": "No updated text available for this card.",
    "Vegas": "No updated text available for this card.",
    "Meadowlands": "No updated text available for this card.",
    "FireWater": "No updated text available for this card.",
    "Cat": "No updated text available for this card.",
    "TeleDAD": "No updated text available for this card.",
    "Gladiator": "No updated text available for this card.",
    "ReturnDAD": "No updated text available for this card.",
    "Trooper": "No updated text available for this card.",
    "Circle": "No updated text available for this card.",
    "Stein": "No updated text available for this card.",
    "Base": "3+ Cyberse monsters\r\nNegate any monster effects activated by your opponent during the Battle Phase. (Quick Effect): You can send 1 Cyberse monster from your Deck or Extra Deck to the GY, and if you do, this card gains the Attribute of that monster sent to the GY, also it gains 2500 ATK. You can only use this effect of \"Firewall Dragon Darkfluid - Neo Tempest Terahertz\" once per turn. This card can attack monsters a number of times each Battle Phase, up to the number of different Attributes it has."
  }
}