{
  "id": 69073023,
  "name": "Infinitrack Fortress Megaclops",
  "Stats": {
    "type": "Link Monster",
    "frameType": "link",
    "atk": 4000,
    "race": "Machine",
    "attribute": "EARTH"
  },
  "Rulings": {
    "Edison": "No rulings found for this card. Request new rulings at https://discord.gg/shVJnYJNpg",
    "Tengu": "No rulings found for this card. Request new rulings at https://discord.gg/MmEZSNeTdX",
    "Goat": "No rulings found for this card. Request new rulings at https://discord.gg/shVJnYJNpg",
    "HAT": "No rulings found for this card. Request new rulings at https://discord.gg/shVJnYJNpg",
    "Vegas": "No rulings found for this card. Request new rulings at https://discord.gg/shVJnYJNpg",
    "Meadowlands": "No rulings found for this card. Request new rulings at https://discord.gg/shVJnYJNpg",
    "FireWater": "No rulings found for this card. Request new rulings at https://discord.gg/shVJnYJNpg",
    "Cat": "No rulings found for this card. Request new rulings at https://discord.gg/shVJnYJNpg",
    "TeleDAD": "No rulings found for this card. Request new rulings at https://discord.gg/shVJnYJNpg",
    "Gladiator": "No rulings found for this card. Request new rulings at https://discord.gg/shVJnYJNpg",
    "ReturnDAD": "No rulings found for this card. Request new rulings at https://discord.gg/shVJnYJNpg",
    "Trooper": "No rulings found for this card. Request new rulings at https://discord.gg/shVJnYJNpg",
    "Circle": "No rulings found for this card. Request new rulings at https://discord.gg/shVJnYJNpg",
    "Stein": "No rulings found for this card. Request new rulings at https://discord.gg/shVJnYJNpg",
    "Base": "No rulings found for this card. Request new rulings at https://discord.gg/shVJnYJNpg"
  },
  "PSCT": {
    "Edison": "No rulings available for this card.",
    "Tengu": "No updated text available for this card.",
    "Goat": "No updated text available for this card.",
    "HAT": "No updated text available for this card.",
    "Vegas": "No updated text available for this card.",
    "Meadowlands": "No updated text available for this card.",
    "FireWater": "No updated text available for this card.",
    "Cat": "No updated text available for this card.",
    "TeleDAD": "No updated text available for this card.",
    "Gladiator": "No updated text available for this card.",
    "ReturnDAD": "No updated text available for this card.",
    "Trooper": "No updated text available for this card.",
    "Circle": "No updated text available for this card.",
    "Stein": "No updated text available for this card.",
    "Base": "3 Xyz Monsters\r\nUnaffected by other monsters' effects, except those of Xyz Monsters. Cannot be destroyed by battle, except with an Xyz Monster. You can target 1 Xyz Monster in your GY and 1 card your opponent controls; Special Summon that monster from your GY, and if you do, attach that opponent's card to it as material, also for the rest of this turn, any damage your opponent takes is halved. You can only use this effect of \"Infinitrack Fortress Megaclops\" once per turn."
  }
}