{
  "id": 7934362,
  "name": "Performage Fire Dancer",
  "Stats": {
    "type": "Pendulum Effect Monster",
    "frameType": "effect_pendulum",
    "atk": 1400,
    "def": 1200,
    "level": 4,
    "race": "Spellcaster",
    "attribute": "FIRE"
  },
  "Rulings": {
    "Edison": "No rulings found for this card. Request new rulings at https://discord.gg/shVJnYJNpg",
    "Tengu": "No rulings found for this card. Request new rulings at https://discord.gg/MmEZSNeTdX",
    "Goat": "No rulings available for this card.",
    "HAT": "No rulings available for this card.",
    "Vegas": "No rulings available for this card.",
    "Meadowlands": "No rulings available for this card.",
    "FireWater": "No rulings available for this card.",
    "Cat": "No rulings available for this card.",
    "TeleDAD": "No rulings available for this card.",
    "Gladiator": "No rulings available for this card.",
    "ReturnDAD": "No rulings available for this card.",
    "Trooper": "No rulings available for this card.",
    "Circle": "No rulings available for this card.",
    "Stein": "No rulings available for this card.",
    "Base": "No rulings available for this card."
  },
  "PSCT": {
    "Edison": "No rulings available for this card.",
    "Tengu": "No updated text available for this card.",
    "Goat": "No updated text available for this card.",
    "HAT": "No updated text available for this card.",
    "Vegas": "No updated text available for this card.",
    "Meadowlands": "No updated text available for this card.",
    "FireWater": "No updated text available for this card.",
    "Cat": "No updated text available for this card.",
    "TeleDAD": "No updated text available for this card.",
    "Gladiator": "No updated text available for this card.",
    "ReturnDAD": "No updated text available for this card.",
    "Trooper": "No updated text available for this card.",
    "Circle": "No updated text available for this card.",
    "Stein": "No updated text available for this card.",
    "Base": "[ Pendulum Effect ] \nOnce per turn: You can target 1 \"Performage\" monster you control; if it attacks a Defense Position monster this turn, inflict piercing battle damage to your opponent.\n[ Monster Effect ] \nIf this card is Normal or Special Summoned: You can add 1 \"Performage\" monster from your Deck to your hand, except \"Performage Fire Dancer\". You can only use this effect of \"Performage Fire Dancer\" once per turn. If this card on the field is destroyed by battle or card effect: You can target 1 face-up monster on the field; it loses 500 ATK."
  }
}