{
  "id": 90809975,
  "name": "Toadally Awesome",
  "Stats": {
    "type": "XYZ Monster",
    "frameType": "xyz",
    "atk": 2200,
    "def": 0,
    "level": 2,
    "race": "Aqua",
    "attribute": "WATER"
  },
  "Rulings": {
    "Edison": "No rulings found for this card. Request new rulings at https://discord.gg/shVJnYJNpg",
    "Tengu": "No rulings found for this card. Request new rulings at https://discord.gg/MmEZSNeTdX",
    "Goat": "No rulings found for this card. Request new rulings at https://discord.gg/shVJnYJNpg",
    "HAT": "No rulings found for this card. Request new rulings at https://discord.gg/shVJnYJNpg",
    "Vegas": "No rulings found for this card. Request new rulings at https://discord.gg/shVJnYJNpg",
    "Meadowlands": "No rulings found for this card. Request new rulings at https://discord.gg/shVJnYJNpg",
    "FireWater": "No rulings found for this card. Request new rulings at https://discord.gg/shVJnYJNpg",
    "Cat": "No rulings found for this card. Request new rulings at https://discord.gg/shVJnYJNpg",
    "TeleDAD": "No rulings found for this card. Request new rulings at https://discord.gg/shVJnYJNpg",
    "Gladiator": "No rulings found for this card. Request new rulings at https://discord.gg/shVJnYJNpg",
    "ReturnDAD": "No rulings found for this card. Request new rulings at https://discord.gg/shVJnYJNpg",
    "Trooper": "No rulings found for this card. Request new rulings at https://discord.gg/shVJnYJNpg",
    "Circle": "No rulings found for this card. Request new rulings at https://discord.gg/shVJnYJNpg",
    "Stein": "No rulings found for this card. Request new rulings at https://discord.gg/shVJnYJNpg",
    "Base": "No rulings found for this card. Request new rulings at https://discord.gg/shVJnYJNpg"
  },
  "PSCT": {
    "Edison": "No rulings available for this card.",
    "Tengu": "No updated text available for this card.",
    "Goat": "No updated text available for this card.",
    "HAT": "No updated text available for this card.",
    "Vegas": "No updated text available for this card.",
    "Meadowlands": "No updated text available for this card.",
    "FireWater": "No updated text available for this card.",
    "Cat": "No updated text available for this card.",
    "TeleDAD": "No updated text available for this card.",
    "Gladiator": "No updated text available for this card.",
    "ReturnDAD": "No updated text available for this card.",
    "Trooper": "No updated text available for this card.",
    "Circle": "No updated text available for this card.",
    "Stein": "No updated text available for this card.",
    "Base": "2 Level 2 Aqua-Type monsters\nOnce per turn, during the Standby Phase: You can detach 1 Xyz Material from this card; Special Summon 1 \"Frog\" monster from your Deck. Once per turn, during either player's turn, when your opponent activates a Spell/Trap Card, or monster effect: You can send 1 Aqua-Type monster from your hand or face-up from your field to the Graveyard; negate the activation, and if you do, destroy that card, then you can Set it to your field. If this card is sent to the Graveyard: You can target 1 WATER monster in your Graveyard; add it to your hand."
  }
}